{
  "db_name": "PostgreSQL",
  "query": "\n        INSERT INTO users (username, email, password_hash, is_18_plus)\n        VALUES ($1, $2, $3, $4)\n        RETURNING id, username, email\n        ",
  "describe": {
    "columns": [
      {
        "ordinal": 0,
        "name": "id",
        "type_info": "Uuid"
      },
      {
        "ordinal": 1,
        "name": "username",
        "type_info": "Varchar"
      },
      {
        "ordinal": 2,
        "name": "email",
        "type_info": "Varchar"
      }
    ],
    "parameters": {
      "Left": [
        "Varchar",
        "Varchar",
        "Varchar",
        "Bool"
      ]
    },
    "nullable": [
      false,
      false,
      false
    ]
  },
  "hash": "525276206e678fb6fdfaed56751b5ea8d474d09840ea46a7334c293600aa2552"
}
